pymodes-2.21.dist-info/RECORD
pymodes-2.21.dist-info/WHEEL
pymodes-2.21.dist-info/entry_points.txt
pymodes-2.21.dist-info/METADATA
pymodes-2.21.dist-info/licenses/LICENSE
pyModeS/c_common.pxd
pyModeS/c_common.pyi
pyModeS/c_common.c
pyModeS/__init__.py
pyModeS/common.pyi
pyModeS/.gitignore
pyModeS/py.typed
pyModeS/py_common.py
pyModeS/c_common.pyx
pyModeS/c_common.cpython-310-darwin.so
pyModeS/decoder/acas.py
pyModeS/decoder/els.py
pyModeS/decoder/ehs.py
pyModeS/decoder/allcall.py
pyModeS/decoder/__init__.py
pyModeS/decoder/surv.py
pyModeS/decoder/uncertainty.py
pyModeS/decoder/commb.py
pyModeS/decoder/uplink.py
pyModeS/decoder/adsb.py
pyModeS/decoder/bds/bds10.py
pyModeS/decoder/bds/bds20.py
pyModeS/decoder/bds/bds45.py
pyModeS/decoder/bds/bds61.py
pyModeS/decoder/bds/bds30.py
pyModeS/decoder/bds/bds44.py
pyModeS/decoder/bds/bds05.py
pyModeS/decoder/bds/bds60.py
pyModeS/decoder/bds/bds40.py
pyModeS/decoder/bds/bds50.py
pyModeS/decoder/bds/__init__.py
pyModeS/decoder/bds/bds08.py
pyModeS/decoder/bds/bds09.py
pyModeS/decoder/bds/bds06.py
pyModeS/decoder/bds/bds53.py
pyModeS/decoder/bds/bds17.py
pyModeS/decoder/bds/bds62.py
pyModeS/decoder/flarm/core.h
pyModeS/decoder/flarm/core.pxd
pyModeS/decoder/flarm/decode.pyx
pyModeS/decoder/flarm/decode.c
pyModeS/decoder/flarm/__init__.py
pyModeS/decoder/flarm/core.c
pyModeS/decoder/flarm/decode.cpython-310-darwin.so
pyModeS/decoder/flarm/decode.pyi
pyModeS/streamer/screen.py
pyModeS/streamer/__init__.py
pyModeS/streamer/modeslive.py
pyModeS/streamer/decode.py
pyModeS/streamer/source.py
pyModeS/extra/__init__.py
pyModeS/extra/aero.py
pyModeS/extra/rtlreader.py
pyModeS/extra/tcpclient.py
