Metadata-Version: 2.4
Name: pyModeS
Version: 2.21
Summary: Python Mode-S and ADS-B Decoder
Project-URL: homepage, https://mode-s.org
Project-URL: repository, https://github.com/junzis/pyModeS
Project-URL: issues, https://github.com/junzis/pyModeS/issues
Author-email: Junzi Sun <git@junzis.com>
License: GNU GPL v3
License-File: LICENSE
Classifier: Development Status :: 4 - Beta
Classifier: Intended Audience :: Developers
Classifier: License :: OSI Approved :: GNU General Public License v3 (GPLv3)
Classifier: Programming Language :: Python :: 3
Classifier: Topic :: Software Development :: Libraries
Classifier: Typing :: Typed
Requires-Python: >=3.9
Requires-Dist: numpy>=1.26
Requires-Dist: pyzmq>=24.0
Provides-Extra: rtlsdr
Requires-Dist: pyrtlsdr>=0.2.93; extra == 'rtlsdr'
